oscn/__init__.py
oscn/_meta.py
oscn/find/__init__.py
oscn/find/parse.py
oscn/find/searches.py
oscn/parse/__init__.py
oscn/parse/_helpers.py
oscn/parse/attorneys.py
oscn/parse/body.py
oscn/parse/bs4_attorneys.py
oscn/parse/bs4_cmids.py
oscn/parse/bs4_counts.py
oscn/parse/bs4_docket.py
oscn/parse/bs4_events.py
oscn/parse/bs4_issues.py
oscn/parse/bs4_parties.py
oscn/parse/cmids.py
oscn/parse/counts.py
oscn/parse/dates.py
oscn/parse/docket.py
oscn/parse/docket_report.py
oscn/parse/documents.py
oscn/parse/events.py
oscn/parse/issues.py
oscn/parse/judge.py
oscn/parse/parties.py
oscn/parse/party_addresses.py
oscn/parse/party_profile.py
oscn/parse/party_properties.py
oscn/parse/style.py
oscn/request/__init__.py
oscn/request/cases.py
oscn/request/docket.py
oscn/request/parties.py
oscn/settings.py
oscn-0.0.95.dist-info/LICENSE.txt
oscn-0.0.95.dist-info/METADATA
oscn-0.0.95.dist-info/WHEEL
oscn-0.0.95.dist-info/RECORD
