Metadata-Version: 2.3
Name: oscn
Version: 0.0.95
Summary: Oklahoma State Courts Network case parsing utilities
License: MIT
Author: John Dungan
Author-email: john@docket2me.com
Requires-Python: >=3.9
Classifier: License :: OSI Approved :: MIT License
Classifier: Programming Language :: Python :: 3
Classifier: Programming Language :: Python :: 3.9
Classifier: Programming Language :: Python :: 3.10
Classifier: Programming Language :: Python :: 3.11
Classifier: Programming Language :: Python :: 3.12
Classifier: Programming Language :: Python :: 3.13
Classifier: Programming Language :: Python :: 3.8
Requires-Dist: beautifulsoup4
Requires-Dist: python-dotenv (>=1.1.1,<2.0.0)
Requires-Dist: requests
Requires-Dist: selectolax
Project-URL: Homepage, https://github.com/codefortulsa/oscn
